plover_spanish_mqd/__init__.py
plover_spanish_mqd/spanish_mqd_double.py
plover_spanish_mqd/spanish_mqd_single.py
plover_spanish_mqd/system.py
plover_spanish_mqd/dictionaries/initial.json
plover_spanish_mqd/dictionaries/punctuation.json
plover_spanish_mqd/dictionaries/spanish_mqd.py
plover_spanish_mqd/dictionaries/user_es.json
plover_spanish_mqd-2.1.7.dist-info/LICENSE
plover_spanish_mqd-2.1.7.dist-info/METADATA
plover_spanish_mqd-2.1.7.dist-info/WHEEL
plover_spanish_mqd-2.1.7.dist-info/entry_points.txt
plover_spanish_mqd-2.1.7.dist-info/top_level.txt
plover_spanish_mqd-2.1.7.dist-info/zip-safe
plover_spanish_mqd-2.1.7.dist-info/RECORD
