Metadata-Version: 2.1
Name: plover-spanish-mqd
Version: 2.1.7
Summary: Support for plover in Spanish (Melany system)
Home-page: https://github.com/nvdaes/plover_spanish_mqd
Author: Noelia Ruiz
Author-email: nrm1977@gmail.com
License: GNU General Public License v3 or later (GPLv3+)
Project-URL: Source Code, https://github.com/nvdaes/plover_spanish_mqd
Project-URL: Issue Tracker, https://github.com/nvdaes/plover_spanish_mqd/issues
Keywords: plover plover_plugin
Platform: UNKNOWN
Classifier: Development Status :: 5 - Production/Stable
Classifier: Environment :: Plugins
Classifier: Intended Audience :: End Users/Desktop
Classifier: License :: OSI Approved :: GNU General Public License v3 or later (GPLv3+)
Classifier: Operating System :: OS Independent
Classifier: Programming Language :: Python :: 3
Classifier: Programming Language :: Python :: 3.6
Classifier: Programming Language :: Python :: 3.7
Classifier: Programming Language :: Python :: 3.8
Classifier: Programming Language :: Python :: 3.9
Classifier: Programming Language :: Python :: 3.10
Requires-Dist: plover (~=4.0.0.dev10)
Requires-Dist: plover-python-dictionary (<2,>=1)
Provides-Extra: lint
Requires-Dist: flake8 (~=3.7.7) ; extra == 'lint'
Requires-Dist: flake8-tabs (==2.1.0) ; extra == 'lint'
Provides-Extra: test
Requires-Dist: plover (~=4.0.0.dev10) ; extra == 'test'
Requires-Dist: pytest (>=3.0.1) ; extra == 'test'
Provides-Extra: type
Requires-Dist: mypy (==0.910) ; extra == 'type'
